{
  "kind": "collectionType",
  "collectionName": "pages",
  "info": {
    "singularName": "page",
    "pluralName": "pages",
    "displayName": "Page"
  },
  "options": {
    "draftAndPublish": true
  },
  "attributes": {
    "slug": {
      "type": "uid"
    },
    "title": {
      "type": "string"
    },
    "img": {
      "allowedTypes": [
        "images",
        "files",
        "videos",
        "audios"
      ],
      "type": "media",
      "multiple": true
    },
    "description": {
      "type": "text"
    }
  }
}
